[
  {
    "name": "推叩叮",
    "img": "./assets/projects/a.jpg"
  },
  {
    "name": "跑酷吃金幣",
    "img": "./assets/projects/b.jpg"
  },
  {
    "name": "彈力球大賽",
    "img": "./assets/projects/c.jpg"
  },
  {
    "name": "飛機",
    "img": "./assets/projects/d.jpg"
  },
  {
    "name": "飛行訓練",
    "img": "./assets/projects/e.jpg"
  },
  {
    "name": "火箭推進",
    "img": "./assets/projects/f.jpg"
  },
  {
    "name": "終結叩叮",
    "img": "./assets/projects/g.jpg"
  },
  {
    "name": "時鐘",
    "img": "./assets/projects/h.jpg"
  },
  {
    "name": "聖誕樹",
    "img": "./assets/projects/i.jpg"
  },
  {
    "name": "射氣球",
    "img": "./assets/projects/j.jpg"
  },
  {
    "name": "大安森林公園",
    "img": "./assets/projects/k.jpg"
  },
  {
    "name": "電流集集棒",
    "img": "./assets/projects/l.jpg"
  },
  {
    "name": "牛仔對決",
    "img": "./assets/projects/m.jpg"
  },
  {
    "name": "鬼魂",
    "img": "./assets/projects/n.jpg"
  },
  {
    "name": "終極密碼",
    "img": "./assets/projects/o.jpg"
  },
  {
    "name": "月亮公轉",
    "img": "./assets/projects/p.jpg"
  },
  {
    "name": "下雪",
    "img": "./assets/projects/q.jpg"
  },
  {
    "name": "彈力球大賽",
    "img": "./assets/projects/r.jpg"
  },
  {
    "name": "飛行訓練",
    "img": "./assets/projects/s.jpg"
  },
  {
    "name": "殭屍",
    "img": "./assets/projects/t.jpg"
  },
  {
    "name": "時鐘",
    "img": "./assets/projects/u.jpg"
  },
  {
    "name": "皮卡丘打排球",
    "img": "./assets/projects/v.jpg"
  },
  {
    "name": "賽車",
    "img": "./assets/projects/w.jpg"
  },
  {
    "name": "秋名山賽道",
    "img": "./assets/projects/x.jpg"
  },
  {
    "name": "小朋友下樓梯",
    "img": "./assets/projects/y.jpg"
  },
  {
    "name": "射氣球",
    "img": "./assets/projects/z.jpg"
  }
]